arxivs/__init__.py
arxivs/arxiv_util.py
arxivs-0.0.1.dist-info/LICENSE
arxivs-0.0.1.dist-info/METADATA
arxivs-0.0.1.dist-info/WHEEL
arxivs-0.0.1.dist-info/top_level.txt
arxivs-0.0.1.dist-info/zip-safe
arxivs-0.0.1.dist-info/RECORD
