Metadata-Version: 2.1
Name: arxivs
Version: 0.0.1
Summary: Get arXiv AI paper.
Home-page: https://github.com/dovolopor-research/arxivs
Author: Ailln
Author-email: kinggreenhall@gmail.com
License: MIT License
Platform: UNKNOWN
Classifier: Programming Language :: Python :: 3
Classifier: License :: OSI Approved :: MIT License
Classifier: Operating System :: OS Independent
Requires-Python: >=3.6
Requires-Dist: feedparser (>=5.2.1)
Requires-Dist: pytz (==2019.1)
